three_x_pay_sdk/__init__.py
three_x_pay_sdk/client.py
three_x_pay_sdk/exceptions.py
three_x_pay_sdk/models.py
three_x_pay_sdk/py.typed
three_x_pay_sdk/webhook.py
three_x_pay_sdk-1.1.1.dist-info/LICENSE
three_x_pay_sdk-1.1.1.dist-info/METADATA
three_x_pay_sdk-1.1.1.dist-info/WHEEL
three_x_pay_sdk-1.1.1.dist-info/RECORD
