Metadata-Version: 2.1
Name: three-x-pay-sdk
Version: 1.1.1
Summary: Python SDK for 3X PAY API
Home-page: https://github.com/enveloss/3x-pay-sdk
License: MIT
Keywords: payments,crypto,sdk,api,3xpay
Requires-Python: >=3.8,<4.0
Classifier: Intended Audience :: Developers
Classifier: License :: OSI Approved :: MIT License
Classifier: Programming Language :: Python :: 3
Classifier: Programming Language :: Python :: 3.8
Classifier: Programming Language :: Python :: 3.9
Classifier: Programming Language :: Python :: 3.10
Classifier: Programming Language :: Python :: 3.11
Classifier: Programming Language :: Python :: 3.12
Classifier: Programming Language :: Python :: 3 :: Only
Classifier: Topic :: Software Development :: Libraries
Classifier: Typing :: Typed
Requires-Dist: httpx (>=0.24,<1.0)
Requires-Dist: pydantic (>=2.5,<3.0)
Project-URL: Repository, https://github.com/enveloss/3x-pay-sdk
